asgi2gulp.py
asgi2gulp-0.1.7.dist-info/LICENSE
asgi2gulp-0.1.7.dist-info/METADATA
asgi2gulp-0.1.7.dist-info/WHEEL
asgi2gulp-0.1.7.dist-info/top_level.txt
asgi2gulp-0.1.7.dist-info/RECORD
