Metadata-Version: 2.1
Name: asgi2gulp
Version: 0.1.7
Summary: Amorphous Structure Generator Interface to GULP
Home-page: https://github.com/ws-qcnssp/asgi2gulp
Author: Wojciech Szczypka
License: MIT License
Platform: UNKNOWN
